bioview/__init__.py
bioview/app.py
bioview/assets/github.png
bioview/assets/icon.png
bioview/biopac/__init__.py
bioview/biopac/controller.py
bioview/biopac/receiver.py
bioview/common/__init__.py
bioview/common/displayer.py
bioview/common/instructions.py
bioview/common/saver.py
bioview/components/__init__.py
bioview/components/annotate_event.py
bioview/components/app_control.py
bioview/components/device_status.py
bioview/components/experiment_settings.py
bioview/components/log_display.py
bioview/components/plot_grid.py
bioview/components/text_dialog.py
bioview/components/usrp_device_config.py
bioview/constants/__init__.py
bioview/constants/biopac.py
bioview/constants/theme.py
bioview/constants/usrp.py
bioview/types/__init__.py
bioview/types/config.py
bioview/types/status.py
bioview/usrp/__init__.py
bioview/usrp/controller.py
bioview/usrp/receiver.py
bioview/usrp/transmitter.py
bioview/utils/__init__.py
bioview/utils/biopac.py
bioview/utils/caches.py
bioview/utils/filter.py
bioview/utils/storage.py
bioview/utils/theme.py
bioview/utils/usrp.py
bioview-0.9.2.dist-info/LICENSE
bioview-0.9.2.dist-info/METADATA
bioview-0.9.2.dist-info/WHEEL
bioview-0.9.2.dist-info/RECORD
