Metadata-Version: 2.3
Name: bioview
Version: 0.9.2
Summary: A versatile, extensible, and performant cross-platform app for biomedical and human-computer interface instrumentation control
License: GPL-v3
Author: Aakash Kapoor
Author-email: 113218196+meowkash@users.noreply.github.com
Requires-Python: >=3.12, <3.13
Classifier: License :: Other/Proprietary License
Classifier: Programming Language :: Python :: 3
Classifier: Programming Language :: Python :: 3.12
Requires-Dist: darkdetect (>=0.8.0,<0.9.0)
Requires-Dist: h5py (>=3.13.0,<4.0.0)
Requires-Dist: matplotlib (>=3.10.1,<4.0.0)
Requires-Dist: numpy (<2.0.0)
Requires-Dist: pygame (>=2.6.1,<3.0.0)
Requires-Dist: pyqt6 (>=6.9.0,<7.0.0)
Requires-Dist: pyqtgraph (>=0.13.7,<0.14.0)
Requires-Dist: qtawesome (>=1.4.0,<2.0.0)
Requires-Dist: scipy (>=1.15.2,<2.0.0)
Requires-Dist: uhd (>=4.8.0.0,<5.0.0.0) ; sys_platform == "win32"
